translation_builder/__init__.py
translation_builder/__main__.py
translation_builder/_builder.py
translation_builder/errors.py
translation_builder-1.0.4.dist-info/LICENSE
translation_builder-1.0.4.dist-info/METADATA
translation_builder-1.0.4.dist-info/WHEEL
translation_builder-1.0.4.dist-info/entry_points.txt
translation_builder-1.0.4.dist-info/top_level.txt
translation_builder-1.0.4.dist-info/RECORD
