Metadata-Version: 2.1
Name: translation-builder
Version: 1.0.4
Summary: A tool for generating Python classes from YAML files
Home-page: https://github.com/Komo4ekoI/translations-builder
Author: Vadym Teliatnyk
Author-email: laivhakin@gmail.com
Project-URL: Documentation, https://github.com/Komo4ekoI/translations-builder
Project-URL: Bug Reports, https://github.com/Komo4ekoI/translations-builder/issues
Project-URL: Source Code, https://github.com/Komo4ekoI/translations-builder
Keywords: package,translation,translator,komo4ek,convert,convertor,builder,translation-builder,translation-generator,g-translation
Classifier: Development Status :: 5 - Production/Stable
Classifier: Intended Audience :: Developers
Classifier: Programming Language :: Python :: 3.8
Classifier: Programming Language :: Python :: 3.9
Classifier: Programming Language :: Python :: 3.10
Classifier: Programming Language :: Python :: 3.11
Classifier: Programming Language :: Python :: 3.12
Classifier: Programming Language :: Python :: 3 :: Only
Classifier: License :: OSI Approved :: Apache Software License
Classifier: Topic :: Software Development :: Code Generators
Requires-Python: >=3.8
License-File: LICENSE
Requires-Dist: PyYAML ==6.0.2
Requires-Dist: black ==24.8.0
